aa_theme_zima/__init__.py
aa_theme_zima/apps.py
aa_theme_zima/static/aa_theme_zima/css/dashboard-dark.css
aa_theme_zima/static/aa_theme_zima/css/dashboard-light.css
aa_theme_zima/static/aa_theme_zima/css/login-page.css
aa_theme_zima/static/aa_theme_zima/icons/android-chrome-192x192.png
aa_theme_zima/static/aa_theme_zima/icons/android-chrome-36x36.png
aa_theme_zima/static/aa_theme_zima/icons/android-chrome-48x48.png
aa_theme_zima/static/aa_theme_zima/icons/apple-touch-icon-57x57.png
aa_theme_zima/static/aa_theme_zima/icons/apple-touch-icon.png
aa_theme_zima/static/aa_theme_zima/icons/favicon-16x16.png
aa_theme_zima/static/aa_theme_zima/icons/favicon-32x32.png
aa_theme_zima/static/aa_theme_zima/icons/favicon.ico
aa_theme_zima/static/aa_theme_zima/img/eve-sso-login-black-large.png
aa_theme_zima/static/aa_theme_zima/img/eve-sso-login-white-large.png
aa_theme_zima/templates/allianceauth/base.html
aa_theme_zima/templates/allianceauth/icons.html
aa_theme_zima/templates/allianceauth/top-menu.html
aa_theme_zima/templates/mumbletemps/link.html
aa_theme_zima/templates/mumbletemps/login.html
aa_theme_zima/templates/public/base.html
aa_theme_zima/templates/public/login.html
aa_theme_zima/templates/public/middle_box.html
aa_theme_zima-0.2.4.dist-info/LICENSE
aa_theme_zima-0.2.4.dist-info/METADATA
aa_theme_zima-0.2.4.dist-info/WHEEL
aa_theme_zima-0.2.4.dist-info/RECORD
