Metadata-Version: 2.1
Name: aa-theme-zima
Version: 0.2.4
Summary: Theme for zimacorp.space
Home-page: https://gitlab.com/zima-corp/aa-theme-zima
License: GPL-3.0-or-later
Author: Boris Talovikov
Author-email: boris@talovikov.ru
Requires-Python: >=3.8,<4.0
Classifier: License :: OSI Approved :: GNU General Public License v3 or later (GPLv3+)
Classifier: Programming Language :: Python :: 3
Classifier: Programming Language :: Python :: 3.8
Classifier: Programming Language :: Python :: 3.9
Classifier: Programming Language :: Python :: 3.10
Classifier: Programming Language :: Python :: 3.11
Classifier: Programming Language :: Python :: 3.12
Requires-Dist: allianceauth (>=3.6)
Project-URL: Repository, https://gitlab.com/zima-corp/aa-theme-zima
